popolo/__init__.py
popolo/admin.py
popolo/models.py
popolo/querysets.py
popolo/urls.py
popolo/views.py
popolo/behaviors/__init__.py
popolo/behaviors/admin.py
popolo/behaviors/models.py
popolo/behaviors/tests.py
popolo/importers/__init__.py
popolo/importers/popit.py
popolo/importers/popolo_json.py
popolo/management/__init__.py
popolo/management/commands/__init__.py
popolo/management/commands/popolo_create_from_popit.py
popolo/migrations/0001_initial.py
popolo/migrations/0002_update_models_from_upstream.py
popolo/migrations/__init__.py
popolo/templates/membership_detail.html
popolo/templates/organization_detail.html
popolo/templates/person_detail.html
popolo/templates/post_detail.html
popolo/tests/__init__.py
popolo/tests/test_importer.py
popolo/tests/test_models.py
mysociety_django_popolo-0.1.0.dist-info/AUTHORS
mysociety_django_popolo-0.1.0.dist-info/LICENSE
mysociety_django_popolo-0.1.0.dist-info/METADATA
mysociety_django_popolo-0.1.0.dist-info/WHEEL
mysociety_django_popolo-0.1.0.dist-info/top_level.txt
mysociety_django_popolo-0.1.0.dist-info/RECORD
