Metadata-Version: 2.1
Name: mysociety-django-popolo
Version: 0.1.0
Summary: A Django-based implementation of the Popolo data specifications.
Home-page: http://github.com/mysociety/django-popolo
Author: Matthew Somerville
Author-email: matthew@mysociety.org
License: Affero
Platform: UNKNOWN
Classifier: Topic :: Internet :: WWW/HTTP :: Dynamic Content
Classifier: Intended Audience :: Developers
Classifier: Programming Language :: Python
Classifier: Programming Language :: Python :: 2
Classifier: Programming Language :: Python :: 3
Classifier: Framework :: Django
Classifier: Development Status :: 5 - Production/Stable
Classifier: Operating System :: OS Independent
Requires-Dist: django-model-utils
